asciicards.py
asciicards-0.0.8.1.dist-info/LICENSE
asciicards-0.0.8.1.dist-info/METADATA
asciicards-0.0.8.1.dist-info/WHEEL
asciicards-0.0.8.1.dist-info/top_level.txt
asciicards-0.0.8.1.dist-info/RECORD
