Metadata-Version: 2.1
Name: asciicards
Version: 0.0.8.1
Summary: Ascii Card Library
Author-email: Paper <none@none.com>
Maintainer-email: Paper <none@none.com>
License: GNU GENERAL PUBLIC LICENSE
Keywords: Ascii,poker,blackjack
Classifier: Development Status :: 4 - Beta
Classifier: Programming Language :: Python
Requires-Python: >=3.8
License-File: LICENSE
